{"version":2,"url_overrides":{"newTabURL":{"initialValue":"about:newtab","precedenceList":[{"id":"newtaboverride@agenedia.com","installDate":1642210273721,"value":"moz-extension://0ec58317-846b-436d-bf11-1767baa8d9ad/html/newtab.html","enabled":true}]}},"prefs":{"websites.hyperlinkAuditingEnabled":{"initialValue":{},"precedenceList":[{"id":"uBlock0@raymondhill.net","installDate":1642210166672,"value":false,"enabled":true}]},"network.networkPredictionEnabled":{"initialValue":{},"precedenceList":[{"id":"uBlock0@raymondhill.net","installDate":1642210166672,"value":false,"enabled":true}]}},"homepageNotification":{},"tabHideNotification":{},"default_search":{},"newTabNotification":{},"commands":{"_execute_browser_action":{"precedenceList":[{"id":"Tab-Session-Manager@sienori","installDate":1642210260857,"value":{"shortcut":"Ctrl+Shift+L"},"enabled":true}]},"saveAllWindow":{"precedenceList":[{"id":"Tab-Session-Manager@sienori","installDate":1642210260857,"value":{},"enabled":true}]},"saveCurrentWindow":{"precedenceList":[{"id":"Tab-Session-Manager@sienori","installDate":1642210260857,"value":{},"enabled":true}]},"exportSessions":{"precedenceList":[{"id":"Tab-Session-Manager@sienori","installDate":1642210260857,"value":{},"enabled":true}]}}}